myfunctions_aziz200115/__init__.py
myfunctions_aziz200115/math.py
myfunctions_aziz200115-0.0.8.dist-info/METADATA
myfunctions_aziz200115-0.0.8.dist-info/WHEEL
myfunctions_aziz200115-0.0.8.dist-info/top_level.txt
myfunctions_aziz200115-0.0.8.dist-info/RECORD
